zenoh_cli.py
zenoh_cli-0.6.8.dist-info/licenses/LICENSE
zenoh_cli-0.6.8.dist-info/METADATA
zenoh_cli-0.6.8.dist-info/WHEEL
zenoh_cli-0.6.8.dist-info/entry_points.txt
zenoh_cli-0.6.8.dist-info/top_level.txt
zenoh_cli-0.6.8.dist-info/RECORD
