Metadata-Version: 2.4
Name: zenoh-cli
Version: 0.6.8
Summary: CLI for Zenoh
Author-email: Fredrik Olsson <fredrik.x.olsson@ri.se>
Maintainer-email: Fredrik Olsson <fredrik.x.olsson@ri.se>
License: Apache License 2.0
Project-URL: Homepage, https://github.com/RISE-Maritime/zenoh-cli
Requires-Python: >=3.9
License-File: LICENSE
Requires-Dist: eclipse-zenoh>=1.2.1
Requires-Dist: parse
Requires-Dist: networkx
Requires-Dist: matplotlib
Requires-Dist: jsonpointer
Requires-Dist: importlib_metadata; python_version < "3.10"
Dynamic: license-file
